mcp_everything_search/__init__.py
mcp_everything_search/__main__.py
mcp_everything_search/server.py
mcp_everything_search-0.2.1.dist-info/METADATA
mcp_everything_search-0.2.1.dist-info/WHEEL
mcp_everything_search-0.2.1.dist-info/entry_points.txt
mcp_everything_search-0.2.1.dist-info/licenses/LICENSE
mcp_everything_search-0.2.1.dist-info/RECORD
