Metadata-Version: 2.4
Name: mcp-everything-search
Version: 0.2.1
Summary: An MCP server for Everything (voidtools) file search
Project-URL: Homepage, https://github.com/essovius/mcp-everything-search
Project-URL: Repository, https://github.com/essovius/mcp-everything-search
Project-URL: Issues, https://github.com/essovius/mcp-everything-search/issues
Author: essovius
License-Expression: MIT
License-File: LICENSE
Keywords: claude,everything,file-search,mcp,voidtools
Classifier: Development Status :: 4 - Beta
Classifier: Intended Audience :: Developers
Classifier: License :: OSI Approved :: MIT License
Classifier: Operating System :: Microsoft :: Windows
Classifier: Programming Language :: Python :: 3
Classifier: Programming Language :: Python :: 3.10
Classifier: Programming Language :: Python :: 3.11
Classifier: Programming Language :: Python :: 3.12
Requires-Python: >=3.10
Requires-Dist: mcp>=1.0.0
